AutoRedis-0.2.1.dist-info/top_level.txt
AutoRedis-0.2.1.dist-info/DESCRIPTION.rst
AutoRedis-0.2.1.dist-info/METADATA
AutoRedis-0.2.1.dist-info/RECORD
AutoRedis-0.2.1.dist-info/metadata.json
AutoRedis-0.2.1.dist-info/WHEEL
autoredis/__init__.py
